NewareNDA/NewareNDA.py
NewareNDA/NewareNDAx.py
NewareNDA/__init__.py
NewareNDA/__main__.py
NewareNDA/dicts.py
NewareNDA/utils.py
NewareNDA/version.py
newarenda-2025.11.3.dist-info/licenses/LICENSE
newarenda-2025.11.3.dist-info/METADATA
newarenda-2025.11.3.dist-info/WHEEL
newarenda-2025.11.3.dist-info/entry_points.txt
newarenda-2025.11.3.dist-info/top_level.txt
newarenda-2025.11.3.dist-info/RECORD
