Metadata-Version: 2.4
Name: NewareNDA
Version: 2025.11.3
Summary: Neware nda binary file reader.
Author-email: Dan Cogswell <cogswell@alum.mit.edu>
License-Expression: BSD-3-Clause
Project-URL: homepage, https://github.com/d-cogswell/NewareNDA
Project-URL: tracker, https://github.com/d-cogswell/NewareNDA/issues
Classifier: Programming Language :: Python :: 3
Requires-Python: >=3.6
License-File: LICENSE
Requires-Dist: pandas
Requires-Dist: importlib-metadata~=1.0; python_version < "3.8"
Provides-Extra: test
Requires-Dist: pytest; extra == "test"
Requires-Dist: pyarrow; extra == "test"
Requires-Dist: coveralls; extra == "test"
Dynamic: license-file
